<annotation>
	<folder>image</folder>
	<filename>329.jpg</filename>
	<path>/home/ostap/Documents/project/ImageWork/Beta1/whiskey cup/countinue/image/329.jpg</path>
	<source>
		<database>Unknown</database>
	</source>
	<size>
		<width>333</width>
		<height>500</height>
		<depth>3</depth>
	</size>
	<segmented>0</segmented>
	<object>
		<name>whiskey</name>
		<pose>Unspecified</pose>
		<truncated>0</truncated>
		<difficult>0</difficult>
		<bndbox>
			<xmin>171</xmin>
			<ymin>174</ymin>
			<xmax>277</xmax>
			<ymax>382</ymax>
		</bndbox>
	</object>
</annotation>
